{
    "data": [
        {
            "type": "gif",
            "id": "3WkiWGcxDXLFaAVPOS",
            "url": "https://giphy.com/gifs/nbclawandorder-nbc-svu-law-and-order-3WkiWGcxDXLFaAVPOS",
            "slug": "nbclawandorder-nbc-svu-law-and-order-3WkiWGcxDXLFaAVPOS",
            "bitly_gif_url": "https://gph.is/g/Ev6Bp5n",
            "bitly_url": "https://gph.is/g/Ev6Bp5n",
            "embed_url": "https://giphy.com/embed/3WkiWGcxDXLFaAVPOS",
            "username": "nbclawandorder",
            "source": "https://www.nbc.com/law-order-hq",
            "title": "Episode 11 Nbc GIF by Law & Order",
            "rating": "g",
            "content_url": "",
            "source_tld": "www.nbc.com",
            "source_post_url": "https://www.nbc.com/law-order-hq",
            "is_sticker": 0,
            "import_datetime": "2022-01-14 18:09:23",
            "trending_datetime": "2022-01-20 22:08:10",
            "images": {
                "original": {
                    "height": "281",
                    "width": "500",
                    "size": "824908",
                    "url": "https://media1.giphy.com/media/3WkiWGcxDXLFaAVPOS/giphy.gif?cid=dc2d95a07pxei7gvj2qojhewywtkvvhfw30h63j7vq9dyhtc&rid=giphy.gif&ct=g",
                    "mp4_size": "169283",
                    "mp4": "https://media1.giphy.com/media/3WkiWGcxDXLFaAVPOS/giphy.mp4?cid=dc2d95a07pxei7gvj2qojhewywtkvvhfw30h63j7vq9dyhtc&rid=giphy.mp4&ct=g",
                    "webp_size": "221536",
                    "webp": "https://media1.giphy.com/media/3WkiWGcxDXLFaAVPOS/giphy.webp?cid=dc2d95a07pxei7gvj2qojhewywtkvvhfw30h63j7vq9dyhtc&rid=giphy.webp&ct=g",
                    "frames": "13",
                    "hash": "25331cfa380fa06a50d8d8416b7fd9a9"
                },
                "downsized": {
                    "height": "281",
                    "width": "500",
                    "size": "824908",
                    "url": "https://media1.giphy.com/media/3WkiWGcxDXLFaAVPOS/giphy.gif?cid=dc2d95a07pxei7gvj2qojhewywtkvvhfw30h63j7vq9dyhtc&rid=giphy.gif&ct=g"
                },
                "downsized_large": {
                    "height": "281",
                    "width": "500",
                    "size": "824908",
                    "url": "https://media1.giphy.com/media/3WkiWGcxDXLFaAVPOS/giphy.gif?cid=dc2d95a07pxei7gvj2qojhewywtkvvhfw30h63j7vq9dyhtc&rid=giphy.gif&ct=g"
                },
                "downsized_medium": {
                    "height": "281",
                    "width": "500",
                    "size": "824908",
                    "url": "https://media1.giphy.com/media/3WkiWGcxDXLFaAVPOS/giphy.gif?cid=dc2d95a07pxei7gvj2qojhewywtkvvhfw30h63j7vq9dyhtc&rid=giphy.gif&ct=g"
                },
                "downsized_small": {
                    "height": "252",
                    "width": "450",
                    "mp4_size": "47134",
                    "mp4": "https://media1.giphy.com/media/3WkiWGcxDXLFaAVPOS/giphy-downsized-small.mp4?cid=dc2d95a07pxei7gvj2qojhewywtkvvhfw30h63j7vq9dyhtc&rid=giphy-downsized-small.mp4&ct=g"
                },
                "downsized_still": {
                    "height": "281",
                    "width": "500",
                    "size": "824908",
                    "url": "https://media1.giphy.com/media/3WkiWGcxDXLFaAVPOS/giphy_s.gif?cid=dc2d95a07pxei7gvj2qojhewywtkvvhfw30h63j7vq9dyhtc&rid=giphy_s.gif&ct=g"
                },
                "fixed_height": {
                    "height": "200",
                    "width": "356",
                    "size": "251158",
                    "url": "https://media1.giphy.com/media/3WkiWGcxDXLFaAVPOS/200.gif?cid=dc2d95a07pxei7gvj2qojhewywtkvvhfw30h63j7vq9dyhtc&rid=200.gif&ct=g",
                    "mp4_size": "68190",
                    "mp4": "https://media1.giphy.com/media/3WkiWGcxDXLFaAVPOS/200.mp4?cid=dc2d95a07pxei7gvj2qojhewywtkvvhfw30h63j7vq9dyhtc&rid=200.mp4&ct=g",
                    "webp_size": "98112",
                    "webp": "https://media1.giphy.com/media/3WkiWGcxDXLFaAVPOS/200.webp?cid=dc2d95a07pxei7gvj2qojhewywtkvvhfw30h63j7vq9dyhtc&rid=200.webp&ct=g"
                },
                "fixed_height_downsampled": {
                    "height": "200",
                    "width": "356",
                    "size": "121627",
                    "url": "https://media1.giphy.com/media/3WkiWGcxDXLFaAVPOS/200_d.gif?cid=dc2d95a07pxei7gvj2qojhewywtkvvhfw30h63j7vq9dyhtc&rid=200_d.gif&ct=g",
                    "webp_size": "77486",
                    "webp": "https://media1.giphy.com/media/3WkiWGcxDXLFaAVPOS/200_d.webp?cid=dc2d95a07pxei7gvj2qojhewywtkvvhfw30h63j7vq9dyhtc&rid=200_d.webp&ct=g"
                },
                "fixed_height_small": {
                    "height": "100",
                    "width": "178",
                    "size": "69766",
                    "url": "https://media1.giphy.com/media/3WkiWGcxDXLFaAVPOS/100.gif?cid=dc2d95a07pxei7gvj2qojhewywtkvvhfw30h63j7vq9dyhtc&rid=100.gif&ct=g",
                    "mp4_size": "19223",
                    "mp4": "https://media1.giphy.com/media/3WkiWGcxDXLFaAVPOS/100.mp4?cid=dc2d95a07pxei7gvj2qojhewywtkvvhfw30h63j7vq9dyhtc&rid=100.mp4&ct=g",
                    "webp_size": "36376",
                    "webp": "https://media1.giphy.com/media/3WkiWGcxDXLFaAVPOS/100.webp?cid=dc2d95a07pxei7gvj2qojhewywtkvvhfw30h63j7vq9dyhtc&rid=100.webp&ct=g"
                },
                "fixed_height_small_still": {
                    "height": "100",
                    "width": "178",
                    "size": "6195",
                    "url": "https://media1.giphy.com/media/3WkiWGcxDXLFaAVPOS/100_s.gif?cid=dc2d95a07pxei7gvj2qojhewywtkvvhfw30h63j7vq9dyhtc&rid=100_s.gif&ct=g"
                },
                "fixed_height_still": {
                    "height": "200",
                    "width": "356",
                    "size": "26332",
                    "url": "https://media1.giphy.com/media/3WkiWGcxDXLFaAVPOS/200_s.gif?cid=dc2d95a07pxei7gvj2qojhewywtkvvhfw30h63j7vq9dyhtc&rid=200_s.gif&ct=g"
                },
                "fixed_width": {
                    "height": "112",
                    "width": "200",
                    "size": "87453",
                    "url": "https://media1.giphy.com/media/3WkiWGcxDXLFaAVPOS/200w.gif?cid=dc2d95a07pxei7gvj2qojhewywtkvvhfw30h63j7vq9dyhtc&rid=200w.gif&ct=g",
                    "mp4_size": "22506",
                    "mp4": "https://media1.giphy.com/media/3WkiWGcxDXLFaAVPOS/200w.mp4?cid=dc2d95a07pxei7gvj2qojhewywtkvvhfw30h63j7vq9dyhtc&rid=200w.mp4&ct=g",
                    "webp_size": "42894",
                    "webp": "https://media1.giphy.com/media/3WkiWGcxDXLFaAVPOS/200w.webp?cid=dc2d95a07pxei7gvj2qojhewywtkvvhfw30h63j7vq9dyhtc&rid=200w.webp&ct=g"
                },
                "fixed_width_downsampled": {
                    "height": "112",
                    "width": "200",
                    "size": "41446",
                    "url": "https://media1.giphy.com/media/3WkiWGcxDXLFaAVPOS/200w_d.gif?cid=dc2d95a07pxei7gvj2qojhewywtkvvhfw30h63j7vq9dyhtc&rid=200w_d.gif&ct=g",
                    "webp_size": "29830",
                    "webp": "https://media1.giphy.com/media/3WkiWGcxDXLFaAVPOS/200w_d.webp?cid=dc2d95a07pxei7gvj2qojhewywtkvvhfw30h63j7vq9dyhtc&rid=200w_d.webp&ct=g"
                },
                "fixed_width_small": {
                    "height": "56",
                    "width": "100",
                    "size": "28945",
                    "url": "https://media1.giphy.com/media/3WkiWGcxDXLFaAVPOS/100w.gif?cid=dc2d95a07pxei7gvj2qojhewywtkvvhfw30h63j7vq9dyhtc&rid=100w.gif&ct=g",
                    "mp4_size": "7971",
                    "mp4": "https://media1.giphy.com/media/3WkiWGcxDXLFaAVPOS/100w.mp4?cid=dc2d95a07pxei7gvj2qojhewywtkvvhfw30h63j7vq9dyhtc&rid=100w.mp4&ct=g",
                    "webp_size": "16780",
                    "webp": "https://media1.giphy.com/media/3WkiWGcxDXLFaAVPOS/100w.webp?cid=dc2d95a07pxei7gvj2qojhewywtkvvhfw30h63j7vq9dyhtc&rid=100w.webp&ct=g"
                },
                "fixed_width_small_still": {
                    "height": "56",
                    "width": "100",
                    "size": "2981",
                    "url": "https://media1.giphy.com/media/3WkiWGcxDXLFaAVPOS/100w_s.gif?cid=dc2d95a07pxei7gvj2qojhewywtkvvhfw30h63j7vq9dyhtc&rid=100w_s.gif&ct=g"
                },
                "fixed_width_still": {
                    "height": "112",
                    "width": "200",
                    "size": "9670",
                    "url": "https://media1.giphy.com/media/3WkiWGcxDXLFaAVPOS/200w_s.gif?cid=dc2d95a07pxei7gvj2qojhewywtkvvhfw30h63j7vq9dyhtc&rid=200w_s.gif&ct=g"
                },
                "looping": {
                    "mp4_size": "1407073",
                    "mp4": "https://media1.giphy.com/media/3WkiWGcxDXLFaAVPOS/giphy-loop.mp4?cid=dc2d95a07pxei7gvj2qojhewywtkvvhfw30h63j7vq9dyhtc&rid=giphy-loop.mp4&ct=g"
                },
                "original_still": {
                    "height": "281",
                    "width": "500",
                    "size": "89811",
                    "url": "https://media1.giphy.com/media/3WkiWGcxDXLFaAVPOS/giphy_s.gif?cid=dc2d95a07pxei7gvj2qojhewywtkvvhfw30h63j7vq9dyhtc&rid=giphy_s.gif&ct=g"
                },
                "original_mp4": {
                    "height": "268",
                    "width": "480",
                    "mp4_size": "169283",
                    "mp4": "https://media1.giphy.com/media/3WkiWGcxDXLFaAVPOS/giphy.mp4?cid=dc2d95a07pxei7gvj2qojhewywtkvvhfw30h63j7vq9dyhtc&rid=giphy.mp4&ct=g"
                },
                "preview": {
                    "height": "134",
                    "width": "239",
                    "mp4_size": "16173",
                    "mp4": "https://media1.giphy.com/media/3WkiWGcxDXLFaAVPOS/giphy-preview.mp4?cid=dc2d95a07pxei7gvj2qojhewywtkvvhfw30h63j7vq9dyhtc&rid=giphy-preview.mp4&ct=g"
                },
                "preview_gif": {
                    "height": "53",
                    "width": "94",
                    "size": "49761",
                    "url": "https://media1.giphy.com/media/3WkiWGcxDXLFaAVPOS/giphy-preview.gif?cid=dc2d95a07pxei7gvj2qojhewywtkvvhfw30h63j7vq9dyhtc&rid=giphy-preview.gif&ct=g"
                },
                "preview_webp": {
                    "height": "116",
                    "width": "206",
                    "size": "34748",
                    "url": "https://media1.giphy.com/media/3WkiWGcxDXLFaAVPOS/giphy-preview.webp?cid=dc2d95a07pxei7gvj2qojhewywtkvvhfw30h63j7vq9dyhtc&rid=giphy-preview.webp&ct=g"
                },
                "480w_still": {
                    "height": "270",
                    "width": "480",
                    "size": "824908",
                    "url": "https://media1.giphy.com/media/3WkiWGcxDXLFaAVPOS/480w_s.jpg?cid=dc2d95a07pxei7gvj2qojhewywtkvvhfw30h63j7vq9dyhtc&rid=480w_s.jpg&ct=g"
                }
            },
            "user": {
                "avatar_url": "https://media3.giphy.com/avatars/nbclawandorder/TrVbERmQcZz3.jpg",
                "banner_image": "https://media3.giphy.com/headers/nbclawandorder/kofW7vhiaOjm.jpg",
                "banner_url": "https://media3.giphy.com/headers/nbclawandorder/kofW7vhiaOjm.jpg",
                "profile_url": "https://giphy.com/nbclawandorder/",
                "username": "nbclawandorder",
                "display_name": "Law & Order",
                "description": "",
                "instagram_url": "https://instagram.com/@nbcsvu",
                "website_url": "https://www.nbc.com/law-and-order-special-victims-unit",
                "is_verified": true
            },
            "analytics_response_payload": "e=Z2lmX2lkPTNXa2lXR2N4RFhMRmFBVlBPUyZldmVudF90eXBlPUdJRl9UUkVORElORyZjaWQ9ZGMyZDk1YTA3cHhlaTdndmoycW9qaGV3eXd0a3Z2aGZ3MzBoNjNqN3ZxOWR5aHRjJmN0PWc",
            "analytics": {
                "onload": {
                    "url": "https://giphy-analytics.giphy.com/v2/pingback_simple?analytics_response_payload=e%3DZ2lmX2lkPTNXa2lXR2N4RFhMRmFBVlBPUyZldmVudF90eXBlPUdJRl9UUkVORElORyZjaWQ9ZGMyZDk1YTA3cHhlaTdndmoycW9qaGV3eXd0a3Z2aGZ3MzBoNjNqN3ZxOWR5aHRjJmN0PWc&action_type=SEEN"
                },
                "onclick": {
                    "url": "https://giphy-analytics.giphy.com/v2/pingback_simple?analytics_response_payload=e%3DZ2lmX2lkPTNXa2lXR2N4RFhMRmFBVlBPUyZldmVudF90eXBlPUdJRl9UUkVORElORyZjaWQ9ZGMyZDk1YTA3cHhlaTdndmoycW9qaGV3eXd0a3Z2aGZ3MzBoNjNqN3ZxOWR5aHRjJmN0PWc&action_type=CLICK"
                },
                "onsent": {
                    "url": "https://giphy-analytics.giphy.com/v2/pingback_simple?analytics_response_payload=e%3DZ2lmX2lkPTNXa2lXR2N4RFhMRmFBVlBPUyZldmVudF90eXBlPUdJRl9UUkVORElORyZjaWQ9ZGMyZDk1YTA3cHhlaTdndmoycW9qaGV3eXd0a3Z2aGZ3MzBoNjNqN3ZxOWR5aHRjJmN0PWc&action_type=SENT"
                }
            }
        },
        {
            "type": "gif",
            "id": "m2fQwSWHsfl26rnSDB",
            "url": "https://giphy.com/gifs/DefyTVNetwork-defy-forged-in-fire-bladesmiths-m2fQwSWHsfl26rnSDB",
            "slug": "DefyTVNetwork-defy-forged-in-fire-bladesmiths-m2fQwSWHsfl26rnSDB",
            "bitly_gif_url": "https://gph.is/g/4AnoGyV",
            "bitly_url": "https://gph.is/g/4AnoGyV",
            "embed_url": "https://giphy.com/embed/m2fQwSWHsfl26rnSDB",
            "username": "DefyTVNetwork",
            "source": "https://www.defytvnet.com/",
            "title": "Sir Yes GIF by DefyTV",
            "rating": "g",
            "content_url": "",
            "source_tld": "www.defytvnet.com",
            "source_post_url": "https://www.defytvnet.com/",
            "is_sticker": 0,
            "import_datetime": "2022-01-12 16:26:09",
            "trending_datetime": "0000-00-00 00:00:00",
            "images": {
                "original": {
                    "height": "270",
                    "width": "480",
                    "size": "481315",
                    "url": "https://media3.giphy.com/media/m2fQwSWHsfl26rnSDB/giphy.gif?cid=dc2d95a07pxei7gvj2qojhewywtkvvhfw30h63j7vq9dyhtc&rid=giphy.gif&ct=g",
                    "mp4_size": "61736",
                    "mp4": "https://media3.giphy.com/media/m2fQwSWHsfl26rnSDB/giphy.mp4?cid=dc2d95a07pxei7gvj2qojhewywtkvvhfw30h63j7vq9dyhtc&rid=giphy.mp4&ct=g",
                    "webp_size": "121832",
                    "webp": "https://media3.giphy.com/media/m2fQwSWHsfl26rnSDB/giphy.webp?cid=dc2d95a07pxei7gvj2qojhewywtkvvhfw30h63j7vq9dyhtc&rid=giphy.webp&ct=g",
                    "frames": "16",
                    "hash": "533534bc358769a738e78da6a38d6579"
                },
                "downsized": {
                    "height": "270",
                    "width": "480",
                    "size": "481315",
                    "url": "https://media3.giphy.com/media/m2fQwSWHsfl26rnSDB/giphy.gif?cid=dc2d95a07pxei7gvj2qojhewywtkvvhfw30h63j7vq9dyhtc&rid=giphy.gif&ct=g"
                },
                "downsized_large": {
                    "height": "270",
                    "width": "480",
                    "size": "481315",
                    "url": "https://media3.giphy.com/media/m2fQwSWHsfl26rnSDB/giphy.gif?cid=dc2d95a07pxei7gvj2qojhewywtkvvhfw30h63j7vq9dyhtc&rid=giphy.gif&ct=g"
                },
                "downsized_medium": {
                    "height": "270",
                    "width": "480",
                    "size": "481315",
                    "url": "https://media3.giphy.com/media/m2fQwSWHsfl26rnSDB/giphy.gif?cid=dc2d95a07pxei7gvj2qojhewywtkvvhfw30h63j7vq9dyhtc&rid=giphy.gif&ct=g"
                },
                "downsized_small": {
                    "height": "270",
                    "width": "480",
                    "mp4_size": "61736",
                    "mp4": "https://media3.giphy.com/media/m2fQwSWHsfl26rnSDB/giphy-downsized-small.mp4?cid=dc2d95a07pxei7gvj2qojhewywtkvvhfw30h63j7vq9dyhtc&rid=giphy-downsized-small.mp4&ct=g"
                },
                "downsized_still": {
                    "height": "270",
                    "width": "480",
                    "size": "481315",
                    "url": "https://media3.giphy.com/media/m2fQwSWHsfl26rnSDB/giphy_s.gif?cid=dc2d95a07pxei7gvj2qojhewywtkvvhfw30h63j7vq9dyhtc&rid=giphy_s.gif&ct=g"
                },
                "fixed_height": {
                    "height": "200",
                    "width": "356",
                    "size": "251359",
                    "url": "https://media3.giphy.com/media/m2fQwSWHsfl26rnSDB/200.gif?cid=dc2d95a07pxei7gvj2qojhewywtkvvhfw30h63j7vq9dyhtc&rid=200.gif&ct=g",
                    "mp4_size": "39091",
                    "mp4": "https://media3.giphy.com/media/m2fQwSWHsfl26rnSDB/200.mp4?cid=dc2d95a07pxei7gvj2qojhewywtkvvhfw30h63j7vq9dyhtc&rid=200.mp4&ct=g",
                    "webp_size": "89838",
                    "webp": "https://media3.giphy.com/media/m2fQwSWHsfl26rnSDB/200.webp?cid=dc2d95a07pxei7gvj2qojhewywtkvvhfw30h63j7vq9dyhtc&rid=200.webp&ct=g"
                },
                "fixed_height_downsampled": {
                    "height": "200",
                    "width": "356",
                    "size": "118939",
                    "url": "https://media3.giphy.com/media/m2fQwSWHsfl26rnSDB/200_d.gif?cid=dc2d95a07pxei7gvj2qojhewywtkvvhfw30h63j7vq9dyhtc&rid=200_d.gif&ct=g",
                    "webp_size": "67930",
                    "webp": "https://media3.giphy.com/media/m2fQwSWHsfl26rnSDB/200_d.webp?cid=dc2d95a07pxei7gvj2qojhewywtkvvhfw30h63j7vq9dyhtc&rid=200_d.webp&ct=g"
                },
                "fixed_height_small": {
                    "height": "100",
                    "width": "178",
                    "size": "90480",
                    "url": "https://media3.giphy.com/media/m2fQwSWHsfl26rnSDB/100.gif?cid=dc2d95a07pxei7gvj2qojhewywtkvvhfw30h63j7vq9dyhtc&rid=100.gif&ct=g",
                    "mp4_size": "15591",
                    "mp4": "https://media3.giphy.com/media/m2fQwSWHsfl26rnSDB/100.mp4?cid=dc2d95a07pxei7gvj2qojhewywtkvvhfw30h63j7vq9dyhtc&rid=100.mp4&ct=g",
                    "webp_size": "35738",
                    "webp": "https://media3.giphy.com/media/m2fQwSWHsfl26rnSDB/100.webp?cid=dc2d95a07pxei7gvj2qojhewywtkvvhfw30h63j7vq9dyhtc&rid=100.webp&ct=g"
                },
                "fixed_height_small_still": {
                    "height": "100",
                    "width": "178",
                    "size": "6907",
                    "url": "https://media3.giphy.com/media/m2fQwSWHsfl26rnSDB/100_s.gif?cid=dc2d95a07pxei7gvj2qojhewywtkvvhfw30h63j7vq9dyhtc&rid=100_s.gif&ct=g"
                },
                "fixed_height_still": {
                    "height": "200",
                    "width": "356",
                    "size": "18327",
                    "url": "https://media3.giphy.com/media/m2fQwSWHsfl26rnSDB/200_s.gif?cid=dc2d95a07pxei7gvj2qojhewywtkvvhfw30h63j7vq9dyhtc&rid=200_s.gif&ct=g"
                },
                "fixed_width": {
                    "height": "113",
                    "width": "200",
                    "size": "101610",
                    "url": "https://media3.giphy.com/media/m2fQwSWHsfl26rnSDB/200w.gif?cid=dc2d95a07pxei7gvj2qojhewywtkvvhfw30h63j7vq9dyhtc&rid=200w.gif&ct=g",
                    "mp4_size": "17356",
                    "mp4": "https://media3.giphy.com/media/m2fQwSWHsfl26rnSDB/200w.mp4?cid=dc2d95a07pxei7gvj2qojhewywtkvvhfw30h63j7vq9dyhtc&rid=200w.mp4&ct=g",
                    "webp_size": "40230",
                    "webp": "https://media3.giphy.com/media/m2fQwSWHsfl26rnSDB/200w.webp?cid=dc2d95a07pxei7gvj2qojhewywtkvvhfw30h63j7vq9dyhtc&rid=200w.webp&ct=g"
                },
                "fixed_width_downsampled": {
                    "height": "113",
                    "width": "200",
                    "size": "46003",
                    "url": "https://media3.giphy.com/media/m2fQwSWHsfl26rnSDB/200w_d.gif?cid=dc2d95a07pxei7gvj2qojhewywtkvvhfw30h63j7vq9dyhtc&rid=200w_d.gif&ct=g",
                    "webp_size": "29406",
                    "webp": "https://media3.giphy.com/media/m2fQwSWHsfl26rnSDB/200w_d.webp?cid=dc2d95a07pxei7gvj2qojhewywtkvvhfw30h63j7vq9dyhtc&rid=200w_d.webp&ct=g"
                },
                "fixed_width_small": {
                    "height": "57",
                    "width": "100",
                    "size": "37934",
                    "url": "https://media3.giphy.com/media/m2fQwSWHsfl26rnSDB/100w.gif?cid=dc2d95a07pxei7gvj2qojhewywtkvvhfw30h63j7vq9dyhtc&rid=100w.gif&ct=g",
                    "mp4_size": "7415",
                    "mp4": "https://media3.giphy.com/media/m2fQwSWHsfl26rnSDB/100w.mp4?cid=dc2d95a07pxei7gvj2qojhewywtkvvhfw30h63j7vq9dyhtc&rid=100w.mp4&ct=g",
                    "webp_size": "15760",
                    "webp": "https://media3.giphy.com/media/m2fQwSWHsfl26rnSDB/100w.webp?cid=dc2d95a07pxei7gvj2qojhewywtkvvhfw30h63j7vq9dyhtc&rid=100w.webp&ct=g"
                },
                "fixed_width_small_still": {
                    "height": "57",
                    "width": "100",
                    "size": "3257",
                    "url": "https://media3.giphy.com/media/m2fQwSWHsfl26rnSDB/100w_s.gif?cid=dc2d95a07pxei7gvj2qojhewywtkvvhfw30h63j7vq9dyhtc&rid=100w_s.gif&ct=g"
                },
                "fixed_width_still": {
                    "height": "113",
                    "width": "200",
                    "size": "9320",
                    "url": "https://media3.giphy.com/media/m2fQwSWHsfl26rnSDB/200w_s.gif?cid=dc2d95a07pxei7gvj2qojhewywtkvvhfw30h63j7vq9dyhtc&rid=200w_s.gif&ct=g"
                },
                "looping": {
                    "mp4_size": "778677",
                    "mp4": "https://media3.giphy.com/media/m2fQwSWHsfl26rnSDB/giphy-loop.mp4?cid=dc2d95a07pxei7gvj2qojhewywtkvvhfw30h63j7vq9dyhtc&rid=giphy-loop.mp4&ct=g"
                },
                "original_still": {
                    "height": "270",
                    "width": "480",
                    "size": "39520",
                    "url": "https://media3.giphy.com/media/m2fQwSWHsfl26rnSDB/giphy_s.gif?cid=dc2d95a07pxei7gvj2qojhewywtkvvhfw30h63j7vq9dyhtc&rid=giphy_s.gif&ct=g"
                },
                "original_mp4": {
                    "height": "270",
                    "width": "480",
                    "mp4_size": "61736",
                    "mp4": "https://media3.giphy.com/media/m2fQwSWHsfl26rnSDB/giphy.mp4?cid=dc2d95a07pxei7gvj2qojhewywtkvvhfw30h63j7vq9dyhtc&rid=giphy.mp4&ct=g"
                },
                "preview": {
                    "height": "240",
                    "width": "426",
                    "mp4_size": "23126",
                    "mp4": "https://media3.giphy.com/media/m2fQwSWHsfl26rnSDB/giphy-preview.mp4?cid=dc2d95a07pxei7gvj2qojhewywtkvvhfw30h63j7vq9dyhtc&rid=giphy-preview.mp4&ct=g"
                },
                "preview_gif": {
                    "height": "59",
                    "width": "105",
                    "size": "49523",
                    "url": "https://media3.giphy.com/media/m2fQwSWHsfl26rnSDB/giphy-preview.gif?cid=dc2d95a07pxei7gvj2qojhewywtkvvhfw30h63j7vq9dyhtc&rid=giphy-preview.gif&ct=g"
                },
                "preview_webp": {
                    "height": "168",
                    "width": "298",
                    "size": "46744",
                    "url": "https://media3.giphy.com/media/m2fQwSWHsfl26rnSDB/giphy-preview.webp?cid=dc2d95a07pxei7gvj2qojhewywtkvvhfw30h63j7vq9dyhtc&rid=giphy-preview.webp&ct=g"
                },
                "hd": {
                    "height": "1080",
                    "width": "1920",
                    "mp4_size": "1294685",
                    "mp4": "https://media3.giphy.com/media/m2fQwSWHsfl26rnSDB/giphy-hd.mp4?cid=dc2d95a07pxei7gvj2qojhewywtkvvhfw30h63j7vq9dyhtc&rid=giphy-hd.mp4&ct=g"
                },
                "480w_still": {
                    "height": "270",
                    "width": "480",
                    "size": "481315",
                    "url": "https://media3.giphy.com/media/m2fQwSWHsfl26rnSDB/480w_s.jpg?cid=dc2d95a07pxei7gvj2qojhewywtkvvhfw30h63j7vq9dyhtc&rid=480w_s.jpg&ct=g"
                }
            },
            "user": {
                "avatar_url": "https://media4.giphy.com/avatars/DefyTVNetwork/11MNNUs6zhUJ.jpeg",
                "banner_image": "https://media4.giphy.com/headers/DefyTVNetwork/GzPG1kByzkQV.jpeg",
                "banner_url": "https://media4.giphy.com/headers/DefyTVNetwork/GzPG1kByzkQV.jpeg",
                "profile_url": "https://giphy.com/DefyTVNetwork/",
                "username": "DefyTVNetwork",
                "display_name": "DefyTV",
                "description": "A celebration of audacious individualism, DEFYTV is a network that immerses viewers in the originality and eccentricity of those who cut against the grain.",
                "instagram_url": "",
                "website_url": "",
                "is_verified": true
            },
            "analytics_response_payload": "e=Z2lmX2lkPW0yZlF3U1dIc2ZsMjZyblNEQiZldmVudF90eXBlPUdJRl9UUkVORElORyZjaWQ9ZGMyZDk1YTA3cHhlaTdndmoycW9qaGV3eXd0a3Z2aGZ3MzBoNjNqN3ZxOWR5aHRjJmN0PWc",
            "analytics": {
                "onload": {
                    "url": "https://giphy-analytics.giphy.com/v2/pingback_simple?analytics_response_payload=e%3DZ2lmX2lkPW0yZlF3U1dIc2ZsMjZyblNEQiZldmVudF90eXBlPUdJRl9UUkVORElORyZjaWQ9ZGMyZDk1YTA3cHhlaTdndmoycW9qaGV3eXd0a3Z2aGZ3MzBoNjNqN3ZxOWR5aHRjJmN0PWc&action_type=SEEN"
                },
                "onclick": {
                    "url": "https://giphy-analytics.giphy.com/v2/pingback_simple?analytics_response_payload=e%3DZ2lmX2lkPW0yZlF3U1dIc2ZsMjZyblNEQiZldmVudF90eXBlPUdJRl9UUkVORElORyZjaWQ9ZGMyZDk1YTA3cHhlaTdndmoycW9qaGV3eXd0a3Z2aGZ3MzBoNjNqN3ZxOWR5aHRjJmN0PWc&action_type=CLICK"
                },
                "onsent": {
                    "url": "https://giphy-analytics.giphy.com/v2/pingback_simple?analytics_response_payload=e%3DZ2lmX2lkPW0yZlF3U1dIc2ZsMjZyblNEQiZldmVudF90eXBlPUdJRl9UUkVORElORyZjaWQ9ZGMyZDk1YTA3cHhlaTdndmoycW9qaGV3eXd0a3Z2aGZ3MzBoNjNqN3ZxOWR5aHRjJmN0PWc&action_type=SENT"
                }
            }
        },
        {
            "type": "gif",
            "id": "Pgg7r0Qdy8uxShcojl",
            "url": "https://giphy.com/gifs/firestartermov-Pgg7r0Qdy8uxShcojl",
            "slug": "firestartermov-Pgg7r0Qdy8uxShcojl",
            "bitly_gif_url": "https://gph.is/g/aK38j8o",
            "bitly_url": "https://gph.is/g/aK38j8o",
            "embed_url": "https://giphy.com/embed/Pgg7r0Qdy8uxShcojl",
            "username": "firestartermov",
            "source": "",
            "title": "Scream GIF by Firestarter",
            "rating": "g",
            "content_url": "",
            "source_tld": "",
            "source_post_url": "",
            "is_sticker": 0,
            "import_datetime": "2022-02-23 19:49:59",
            "trending_datetime": "2022-02-24 19:52:07",
            "images": {
                "original": {
                    "height": "270",
                    "width": "480",
                    "size": "497055",
                    "url": "https://media4.giphy.com/media/Pgg7r0Qdy8uxShcojl/giphy.gif?cid=dc2d95a07pxei7gvj2qojhewywtkvvhfw30h63j7vq9dyhtc&rid=giphy.gif&ct=g",
                    "mp4_size": "63166",
                    "mp4": "https://media4.giphy.com/media/Pgg7r0Qdy8uxShcojl/giphy.mp4?cid=dc2d95a07pxei7gvj2qojhewywtkvvhfw30h63j7vq9dyhtc&rid=giphy.mp4&ct=g",
                    "webp_size": "62614",
                    "webp": "https://media4.giphy.com/media/Pgg7r0Qdy8uxShcojl/giphy.webp?cid=dc2d95a07pxei7gvj2qojhewywtkvvhfw30h63j7vq9dyhtc&rid=giphy.webp&ct=g",
                    "frames": "9",
                    "hash": "958ce5a8545b2199c28549aa4d4870e3"
                },
                "downsized": {
                    "height": "270",
                    "width": "480",
                    "size": "497055",
                    "url": "https://media4.giphy.com/media/Pgg7r0Qdy8uxShcojl/giphy.gif?cid=dc2d95a07pxei7gvj2qojhewywtkvvhfw30h63j7vq9dyhtc&rid=giphy.gif&ct=g"
                },
                "downsized_large": {
                    "height": "270",
                    "width": "480",
                    "size": "497055",
                    "url": "https://media4.giphy.com/media/Pgg7r0Qdy8uxShcojl/giphy.gif?cid=dc2d95a07pxei7gvj2qojhewywtkvvhfw30h63j7vq9dyhtc&rid=giphy.gif&ct=g"
                },
                "downsized_medium": {
                    "height": "270",
                    "width": "480",
                    "size": "497055",
                    "url": "https://media4.giphy.com/media/Pgg7r0Qdy8uxShcojl/giphy.gif?cid=dc2d95a07pxei7gvj2qojhewywtkvvhfw30h63j7vq9dyhtc&rid=giphy.gif&ct=g"
                },
                "downsized_small": {
                    "height": "270",
                    "width": "480",
                    "mp4_size": "68773",
                    "mp4": "https://media4.giphy.com/media/Pgg7r0Qdy8uxShcojl/giphy-downsized-small.mp4?cid=dc2d95a07pxei7gvj2qojhewywtkvvhfw30h63j7vq9dyhtc&rid=giphy-downsized-small.mp4&ct=g"
                },
                "downsized_still": {
                    "height": "270",
                    "width": "480",
                    "size": "497055",
                    "url": "https://media4.giphy.com/media/Pgg7r0Qdy8uxShcojl/giphy_s.gif?cid=dc2d95a07pxei7gvj2qojhewywtkvvhfw30h63j7vq9dyhtc&rid=giphy_s.gif&ct=g"
                },
                "fixed_height": {
                    "height": "200",
                    "width": "356",
                    "size": "211455",
                    "url": "https://media4.giphy.com/media/Pgg7r0Qdy8uxShcojl/200.gif?cid=dc2d95a07pxei7gvj2qojhewywtkvvhfw30h63j7vq9dyhtc&rid=200.gif&ct=g",
                    "mp4_size": "40338",
                    "mp4": "https://media4.giphy.com/media/Pgg7r0Qdy8uxShcojl/200.mp4?cid=dc2d95a07pxei7gvj2qojhewywtkvvhfw30h63j7vq9dyhtc&rid=200.mp4&ct=g",
                    "webp_size": "40840",
                    "webp": "https://media4.giphy.com/media/Pgg7r0Qdy8uxShcojl/200.webp?cid=dc2d95a07pxei7gvj2qojhewywtkvvhfw30h63j7vq9dyhtc&rid=200.webp&ct=g"
                },
                "fixed_height_downsampled": {
                    "height": "200",
                    "width": "356",
                    "size": "157890",
                    "url": "https://media4.giphy.com/media/Pgg7r0Qdy8uxShcojl/200_d.gif?cid=dc2d95a07pxei7gvj2qojhewywtkvvhfw30h63j7vq9dyhtc&rid=200_d.gif&ct=g",
                    "webp_size": "92970",
                    "webp": "https://media4.giphy.com/media/Pgg7r0Qdy8uxShcojl/200_d.webp?cid=dc2d95a07pxei7gvj2qojhewywtkvvhfw30h63j7vq9dyhtc&rid=200_d.webp&ct=g"
                },
                "fixed_height_small": {
                    "height": "100",
                    "width": "178",
                    "size": "75053",
                    "url": "https://media4.giphy.com/media/Pgg7r0Qdy8uxShcojl/100.gif?cid=dc2d95a07pxei7gvj2qojhewywtkvvhfw30h63j7vq9dyhtc&rid=100.gif&ct=g",
                    "mp4_size": "15762",
                    "mp4": "https://media4.giphy.com/media/Pgg7r0Qdy8uxShcojl/100.mp4?cid=dc2d95a07pxei7gvj2qojhewywtkvvhfw30h63j7vq9dyhtc&rid=100.mp4&ct=g",
                    "webp_size": "16746",
                    "webp": "https://media4.giphy.com/media/Pgg7r0Qdy8uxShcojl/100.webp?cid=dc2d95a07pxei7gvj2qojhewywtkvvhfw30h63j7vq9dyhtc&rid=100.webp&ct=g"
                },
                "fixed_height_small_still": {
                    "height": "100",
                    "width": "178",
                    "size": "9869",
                    "url": "https://media4.giphy.com/media/Pgg7r0Qdy8uxShcojl/100_s.gif?cid=dc2d95a07pxei7gvj2qojhewywtkvvhfw30h63j7vq9dyhtc&rid=100_s.gif&ct=g"
                },
                "fixed_height_still": {
                    "height": "200",
                    "width": "356",
                    "size": "25388",
                    "url": "https://media4.giphy.com/media/Pgg7r0Qdy8uxShcojl/200_s.gif?cid=dc2d95a07pxei7gvj2qojhewywtkvvhfw30h63j7vq9dyhtc&rid=200_s.gif&ct=g"
                },
                "fixed_width": {
                    "height": "113",
                    "width": "200",
                    "size": "97140",
                    "url": "https://media4.giphy.com/media/Pgg7r0Qdy8uxShcojl/200w.gif?cid=dc2d95a07pxei7gvj2qojhewywtkvvhfw30h63j7vq9dyhtc&rid=200w.gif&ct=g",
                    "mp4_size": "17189",
                    "mp4": "https://media4.giphy.com/media/Pgg7r0Qdy8uxShcojl/200w.mp4?cid=dc2d95a07pxei7gvj2qojhewywtkvvhfw30h63j7vq9dyhtc&rid=200w.mp4&ct=g",
                    "webp_size": "18624",
                    "webp": "https://media4.giphy.com/media/Pgg7r0Qdy8uxShcojl/200w.webp?cid=dc2d95a07pxei7gvj2qojhewywtkvvhfw30h63j7vq9dyhtc&rid=200w.webp&ct=g"
                },
                "fixed_width_downsampled": {
                    "height": "113",
                    "width": "200",
                    "size": "64842",
                    "url": "https://media4.giphy.com/media/Pgg7r0Qdy8uxShcojl/200w_d.gif?cid=dc2d95a07pxei7gvj2qojhewywtkvvhfw30h63j7vq9dyhtc&rid=200w_d.gif&ct=g",
                    "webp_size": "34886",
                    "webp": "https://media4.giphy.com/media/Pgg7r0Qdy8uxShcojl/200w_d.webp?cid=dc2d95a07pxei7gvj2qojhewywtkvvhfw30h63j7vq9dyhtc&rid=200w_d.webp&ct=g"
                },
                "fixed_width_small": {
                    "height": "57",
                    "width": "100",
                    "size": "30052",
                    "url": "https://media4.giphy.com/media/Pgg7r0Qdy8uxShcojl/100w.gif?cid=dc2d95a07pxei7gvj2qojhewywtkvvhfw30h63j7vq9dyhtc&rid=100w.gif&ct=g",
                    "mp4_size": "7492",
                    "mp4": "https://media4.giphy.com/media/Pgg7r0Qdy8uxShcojl/100w.mp4?cid=dc2d95a07pxei7gvj2qojhewywtkvvhfw30h63j7vq9dyhtc&rid=100w.mp4&ct=g",
                    "webp_size": "8000",
                    "webp": "https://media4.giphy.com/media/Pgg7r0Qdy8uxShcojl/100w.webp?cid=dc2d95a07pxei7gvj2qojhewywtkvvhfw30h63j7vq9dyhtc&rid=100w.webp&ct=g"
                },
                "fixed_width_small_still": {
                    "height": "57",
                    "width": "100",
                    "size": "4049",
                    "url": "https://media4.giphy.com/media/Pgg7r0Qdy8uxShcojl/100w_s.gif?cid=dc2d95a07pxei7gvj2qojhewywtkvvhfw30h63j7vq9dyhtc&rid=100w_s.gif&ct=g"
                },
                "fixed_width_still": {
                    "height": "113",
                    "width": "200",
                    "size": "12459",
                    "url": "https://media4.giphy.com/media/Pgg7r0Qdy8uxShcojl/200w_s.gif?cid=dc2d95a07pxei7gvj2qojhewywtkvvhfw30h63j7vq9dyhtc&rid=200w_s.gif&ct=g"
                },
                "looping": {
                    "mp4_size": "2816157",
                    "mp4": "https://media4.giphy.com/media/Pgg7r0Qdy8uxShcojl/giphy-loop.mp4?cid=dc2d95a07pxei7gvj2qojhewywtkvvhfw30h63j7vq9dyhtc&rid=giphy-loop.mp4&ct=g"
                },
                "original_still": {
                    "height": "270",
                    "width": "480",
                    "size": "91177",
                    "url": "https://media4.giphy.com/media/Pgg7r0Qdy8uxShcojl/giphy_s.gif?cid=dc2d95a07pxei7gvj2qojhewywtkvvhfw30h63j7vq9dyhtc&rid=giphy_s.gif&ct=g"
                },
                "original_mp4": {
                    "height": "270",
                    "width": "480",
                    "mp4_size": "63166",
                    "mp4": "https://media4.giphy.com/media/Pgg7r0Qdy8uxShcojl/giphy.mp4?cid=dc2d95a07pxei7gvj2qojhewywtkvvhfw30h63j7vq9dyhtc&rid=giphy.mp4&ct=g"
                },
                "preview": {
                    "height": "228",
                    "width": "405",
                    "mp4_size": "23321",
                    "mp4": "https://media4.giphy.com/media/Pgg7r0Qdy8uxShcojl/giphy-preview.mp4?cid=dc2d95a07pxei7gvj2qojhewywtkvvhfw30h63j7vq9dyhtc&rid=giphy-preview.mp4&ct=g"
                },
                "preview_gif": {
                    "height": "54",
                    "width": "96",
                    "size": "49518",
                    "url": "https://media4.giphy.com/media/Pgg7r0Qdy8uxShcojl/giphy-preview.gif?cid=dc2d95a07pxei7gvj2qojhewywtkvvhfw30h63j7vq9dyhtc&rid=giphy-preview.gif&ct=g"
                },
                "preview_webp": {
                    "height": "222",
                    "width": "394",
                    "size": "42668",
                    "url": "https://media4.giphy.com/media/Pgg7r0Qdy8uxShcojl/giphy-preview.webp?cid=dc2d95a07pxei7gvj2qojhewywtkvvhfw30h63j7vq9dyhtc&rid=giphy-preview.webp&ct=g"
                },
                "hd": {
                    "height": "720",
                    "width": "1280",
                    "mp4_size": "591206",
                    "mp4": "https://media4.giphy.com/media/Pgg7r0Qdy8uxShcojl/giphy-hd.mp4?cid=dc2d95a07pxei7gvj2qojhewywtkvvhfw30h63j7vq9dyhtc&rid=giphy-hd.mp4&ct=g"
                },
                "480w_still": {
                    "height": "270",
                    "width": "480",
                    "size": "497055",
                    "url": "https://media4.giphy.com/media/Pgg7r0Qdy8uxShcojl/480w_s.jpg?cid=dc2d95a07pxei7gvj2qojhewywtkvvhfw30h63j7vq9dyhtc&rid=480w_s.jpg&ct=g"
                }
            },
            "user": {
                "avatar_url": "https://media0.giphy.com/avatars/firestartermov/XXnw80mNWmbn.jpg",
                "banner_image": "",
                "banner_url": "",
                "profile_url": "https://giphy.com/firestartermov/",
                "username": "firestartermov",
                "display_name": "Firestarter",
                "description": "",
                "instagram_url": "https://instagram.com/firestartermov",
                "website_url": "http://Firestartermovie.com",
                "is_verified": true
            },
            "analytics_response_payload": "e=Z2lmX2lkPVBnZzdyMFFkeTh1eFNoY29qbCZldmVudF90eXBlPUdJRl9UUkVORElORyZjaWQ9ZGMyZDk1YTA3cHhlaTdndmoycW9qaGV3eXd0a3Z2aGZ3MzBoNjNqN3ZxOWR5aHRjJmN0PWc",
            "analytics": {
                "onload": {
                    "url": "https://giphy-analytics.giphy.com/v2/pingback_simple?analytics_response_payload=e%3DZ2lmX2lkPVBnZzdyMFFkeTh1eFNoY29qbCZldmVudF90eXBlPUdJRl9UUkVORElORyZjaWQ9ZGMyZDk1YTA3cHhlaTdndmoycW9qaGV3eXd0a3Z2aGZ3MzBoNjNqN3ZxOWR5aHRjJmN0PWc&action_type=SEEN"
                },
                "onclick": {
                    "url": "https://giphy-analytics.giphy.com/v2/pingback_simple?analytics_response_payload=e%3DZ2lmX2lkPVBnZzdyMFFkeTh1eFNoY29qbCZldmVudF90eXBlPUdJRl9UUkVORElORyZjaWQ9ZGMyZDk1YTA3cHhlaTdndmoycW9qaGV3eXd0a3Z2aGZ3MzBoNjNqN3ZxOWR5aHRjJmN0PWc&action_type=CLICK"
                },
                "onsent": {
                    "url": "https://giphy-analytics.giphy.com/v2/pingback_simple?analytics_response_payload=e%3DZ2lmX2lkPVBnZzdyMFFkeTh1eFNoY29qbCZldmVudF90eXBlPUdJRl9UUkVORElORyZjaWQ9ZGMyZDk1YTA3cHhlaTdndmoycW9qaGV3eXd0a3Z2aGZ3MzBoNjNqN3ZxOWR5aHRjJmN0PWc&action_type=SENT"
                }
            }
        },
        {
            "type": "gif",
            "id": "1luY5uKUrILyQbwcKe",
            "url": "https://giphy.com/gifs/coffee-morning-good-1luY5uKUrILyQbwcKe",
            "slug": "coffee-morning-good-1luY5uKUrILyQbwcKe",
            "bitly_gif_url": "https://gph.is/2DoMR0i",
            "bitly_url": "https://gph.is/2DoMR0i",
            "embed_url": "https://giphy.com/embed/1luY5uKUrILyQbwcKe",
            "username": "chippythedog",
            "source": "",
            "title": "Good Morning Hello GIF by Chippy the Dog",
            "rating": "g",
            "content_url": "",
            "source_tld": "",
            "source_post_url": "",
            "is_sticker": 0,
            "import_datetime": "2018-09-23 17:28:28",
            "trending_datetime": "2019-03-28 13:15:02",
            "images": {
                "original": {
                    "height": "480",
                    "width": "470",
                    "size": "1764531",
                    "url": "https://media2.giphy.com/media/1luY5uKUrILyQbwcKe/giphy.gif?cid=dc2d95a07pxei7gvj2qojhewywtkvvhfw30h63j7vq9dyhtc&rid=giphy.gif&ct=g",
                    "mp4_size": "621450",
                    "mp4": "https://media2.giphy.com/media/1luY5uKUrILyQbwcKe/giphy.mp4?cid=dc2d95a07pxei7gvj2qojhewywtkvvhfw30h63j7vq9dyhtc&rid=giphy.mp4&ct=g",
                    "webp_size": "893396",
                    "webp": "https://media2.giphy.com/media/1luY5uKUrILyQbwcKe/giphy.webp?cid=dc2d95a07pxei7gvj2qojhewywtkvvhfw30h63j7vq9dyhtc&rid=giphy.webp&ct=g",
                    "frames": "96",
                    "hash": "2b11241c118966955556520c52c5ebb8"
                },
                "downsized": {
                    "height": "480",
                    "width": "470",
                    "size": "1764531",
                    "url": "https://media2.giphy.com/media/1luY5uKUrILyQbwcKe/giphy.gif?cid=dc2d95a07pxei7gvj2qojhewywtkvvhfw30h63j7vq9dyhtc&rid=giphy.gif&ct=g"
                },
                "downsized_large": {
                    "height": "480",
                    "width": "470",
                    "size": "1764531",
                    "url": "https://media2.giphy.com/media/1luY5uKUrILyQbwcKe/giphy.gif?cid=dc2d95a07pxei7gvj2qojhewywtkvvhfw30h63j7vq9dyhtc&rid=giphy.gif&ct=g"
                },
                "downsized_medium": {
                    "height": "480",
                    "width": "470",
                    "size": "1764531",
                    "url": "https://media2.giphy.com/media/1luY5uKUrILyQbwcKe/giphy.gif?cid=dc2d95a07pxei7gvj2qojhewywtkvvhfw30h63j7vq9dyhtc&rid=giphy.gif&ct=g"
                },
                "downsized_small": {
                    "height": "272",
                    "width": "266",
                    "mp4_size": "160611",
                    "mp4": "https://media2.giphy.com/media/1luY5uKUrILyQbwcKe/giphy-downsized-small.mp4?cid=dc2d95a07pxei7gvj2qojhewywtkvvhfw30h63j7vq9dyhtc&rid=giphy-downsized-small.mp4&ct=g"
                },
                "downsized_still": {
                    "height": "480",
                    "width": "470",
                    "size": "1764531",
                    "url": "https://media2.giphy.com/media/1luY5uKUrILyQbwcKe/giphy_s.gif?cid=dc2d95a07pxei7gvj2qojhewywtkvvhfw30h63j7vq9dyhtc&rid=giphy_s.gif&ct=g"
                },
                "fixed_height": {
                    "height": "200",
                    "width": "196",
                    "size": "452644",
                    "url": "https://media2.giphy.com/media/1luY5uKUrILyQbwcKe/200.gif?cid=dc2d95a07pxei7gvj2qojhewywtkvvhfw30h63j7vq9dyhtc&rid=200.gif&ct=g",
                    "mp4_size": "205365",
                    "mp4": "https://media2.giphy.com/media/1luY5uKUrILyQbwcKe/200.mp4?cid=dc2d95a07pxei7gvj2qojhewywtkvvhfw30h63j7vq9dyhtc&rid=200.mp4&ct=g",
                    "webp_size": "361170",
                    "webp": "https://media2.giphy.com/media/1luY5uKUrILyQbwcKe/200.webp?cid=dc2d95a07pxei7gvj2qojhewywtkvvhfw30h63j7vq9dyhtc&rid=200.webp&ct=g"
                },
                "fixed_height_downsampled": {
                    "height": "200",
                    "width": "196",
                    "size": "59881",
                    "url": "https://media2.giphy.com/media/1luY5uKUrILyQbwcKe/200_d.gif?cid=dc2d95a07pxei7gvj2qojhewywtkvvhfw30h63j7vq9dyhtc&rid=200_d.gif&ct=g",
                    "webp_size": "47100",
                    "webp": "https://media2.giphy.com/media/1luY5uKUrILyQbwcKe/200_d.webp?cid=dc2d95a07pxei7gvj2qojhewywtkvvhfw30h63j7vq9dyhtc&rid=200_d.webp&ct=g"
                },
                "fixed_height_small": {
                    "height": "100",
                    "width": "98",
                    "size": "167761",
                    "url": "https://media2.giphy.com/media/1luY5uKUrILyQbwcKe/100.gif?cid=dc2d95a07pxei7gvj2qojhewywtkvvhfw30h63j7vq9dyhtc&rid=100.gif&ct=g",
                    "mp4_size": "76772",
                    "mp4": "https://media2.giphy.com/media/1luY5uKUrILyQbwcKe/100.mp4?cid=dc2d95a07pxei7gvj2qojhewywtkvvhfw30h63j7vq9dyhtc&rid=100.mp4&ct=g",
                    "webp_size": "127530",
                    "webp": "https://media2.giphy.com/media/1luY5uKUrILyQbwcKe/100.webp?cid=dc2d95a07pxei7gvj2qojhewywtkvvhfw30h63j7vq9dyhtc&rid=100.webp&ct=g"
                },
                "fixed_height_small_still": {
                    "height": "100",
                    "width": "98",
                    "size": "4706",
                    "url": "https://media2.giphy.com/media/1luY5uKUrILyQbwcKe/100_s.gif?cid=dc2d95a07pxei7gvj2qojhewywtkvvhfw30h63j7vq9dyhtc&rid=100_s.gif&ct=g"
                },
                "fixed_height_still": {
                    "height": "200",
                    "width": "196",
                    "size": "11167",
                    "url": "https://media2.giphy.com/media/1luY5uKUrILyQbwcKe/200_s.gif?cid=dc2d95a07pxei7gvj2qojhewywtkvvhfw30h63j7vq9dyhtc&rid=200_s.gif&ct=g"
                },
                "fixed_width": {
                    "height": "204",
                    "width": "200",
                    "size": "467293",
                    "url": "https://media2.giphy.com/media/1luY5uKUrILyQbwcKe/200w.gif?cid=dc2d95a07pxei7gvj2qojhewywtkvvhfw30h63j7vq9dyhtc&rid=200w.gif&ct=g",
                    "mp4_size": "207708",
                    "mp4": "https://media2.giphy.com/media/1luY5uKUrILyQbwcKe/200w.mp4?cid=dc2d95a07pxei7gvj2qojhewywtkvvhfw30h63j7vq9dyhtc&rid=200w.mp4&ct=g",
                    "webp_size": "359248",
                    "webp": "https://media2.giphy.com/media/1luY5uKUrILyQbwcKe/200w.webp?cid=dc2d95a07pxei7gvj2qojhewywtkvvhfw30h63j7vq9dyhtc&rid=200w.webp&ct=g"
                },
                "fixed_width_downsampled": {
                    "height": "204",
                    "width": "200",
                    "size": "60551",
                    "url": "https://media2.giphy.com/media/1luY5uKUrILyQbwcKe/200w_d.gif?cid=dc2d95a07pxei7gvj2qojhewywtkvvhfw30h63j7vq9dyhtc&rid=200w_d.gif&ct=g",
                    "webp_size": "47344",
                    "webp": "https://media2.giphy.com/media/1luY5uKUrILyQbwcKe/200w_d.webp?cid=dc2d95a07pxei7gvj2qojhewywtkvvhfw30h63j7vq9dyhtc&rid=200w_d.webp&ct=g"
                },
                "fixed_width_small": {
                    "height": "102",
                    "width": "100",
                    "size": "174081",
                    "url": "https://media2.giphy.com/media/1luY5uKUrILyQbwcKe/100w.gif?cid=dc2d95a07pxei7gvj2qojhewywtkvvhfw30h63j7vq9dyhtc&rid=100w.gif&ct=g",
                    "mp4_size": "48370",
                    "mp4": "https://media2.giphy.com/media/1luY5uKUrILyQbwcKe/100w.mp4?cid=dc2d95a07pxei7gvj2qojhewywtkvvhfw30h63j7vq9dyhtc&rid=100w.mp4&ct=g",
                    "webp_size": "130860",
                    "webp": "https://media2.giphy.com/media/1luY5uKUrILyQbwcKe/100w.webp?cid=dc2d95a07pxei7gvj2qojhewywtkvvhfw30h63j7vq9dyhtc&rid=100w.webp&ct=g"
                },
                "fixed_width_small_still": {
                    "height": "102",
                    "width": "100",
                    "size": "4853",
                    "url": "https://media2.giphy.com/media/1luY5uKUrILyQbwcKe/100w_s.gif?cid=dc2d95a07pxei7gvj2qojhewywtkvvhfw30h63j7vq9dyhtc&rid=100w_s.gif&ct=g"
                },
                "fixed_width_still": {
                    "height": "204",
                    "width": "200",
                    "size": "11480",
                    "url": "https://media2.giphy.com/media/1luY5uKUrILyQbwcKe/200w_s.gif?cid=dc2d95a07pxei7gvj2qojhewywtkvvhfw30h63j7vq9dyhtc&rid=200w_s.gif&ct=g"
                },
                "looping": {
                    "mp4_size": "1416286",
                    "mp4": "https://media2.giphy.com/media/1luY5uKUrILyQbwcKe/giphy-loop.mp4?cid=dc2d95a07pxei7gvj2qojhewywtkvvhfw30h63j7vq9dyhtc&rid=giphy-loop.mp4&ct=g"
                },
                "original_still": {
                    "height": "480",
                    "width": "470",
                    "size": "44135",
                    "url": "https://media2.giphy.com/media/1luY5uKUrILyQbwcKe/giphy_s.gif?cid=dc2d95a07pxei7gvj2qojhewywtkvvhfw30h63j7vq9dyhtc&rid=giphy_s.gif&ct=g"
                },
                "original_mp4": {
                    "height": "480",
                    "width": "470",
                    "mp4_size": "621450",
                    "mp4": "https://media2.giphy.com/media/1luY5uKUrILyQbwcKe/giphy.mp4?cid=dc2d95a07pxei7gvj2qojhewywtkvvhfw30h63j7vq9dyhtc&rid=giphy.mp4&ct=g"
                },
                "preview": {
                    "height": "374",
                    "width": "366",
                    "mp4_size": "26032",
                    "mp4": "https://media2.giphy.com/media/1luY5uKUrILyQbwcKe/giphy-preview.mp4?cid=dc2d95a07pxei7gvj2qojhewywtkvvhfw30h63j7vq9dyhtc&rid=giphy-preview.mp4&ct=g"
                },
                "preview_gif": {
                    "height": "190",
                    "width": "186",
                    "size": "47863",
                    "url": "https://media2.giphy.com/media/1luY5uKUrILyQbwcKe/giphy-preview.gif?cid=dc2d95a07pxei7gvj2qojhewywtkvvhfw30h63j7vq9dyhtc&rid=giphy-preview.gif&ct=g"
                },
                "preview_webp": {
                    "height": "222",
                    "width": "218",
                    "size": "46730",
                    "url": "https://media2.giphy.com/media/1luY5uKUrILyQbwcKe/giphy-preview.webp?cid=dc2d95a07pxei7gvj2qojhewywtkvvhfw30h63j7vq9dyhtc&rid=giphy-preview.webp&ct=g"
                },
                "hd": {
                    "height": "1920",
                    "width": "1882",
                    "mp4_size": "3232263",
                    "mp4": "https://media2.giphy.com/media/1luY5uKUrILyQbwcKe/giphy-hd.mp4?cid=dc2d95a07pxei7gvj2qojhewywtkvvhfw30h63j7vq9dyhtc&rid=giphy-hd.mp4&ct=g"
                },
                "480w_still": {
                    "height": "490",
                    "width": "480",
                    "size": "1764531",
                    "url": "https://media2.giphy.com/media/1luY5uKUrILyQbwcKe/480w_s.jpg?cid=dc2d95a07pxei7gvj2qojhewywtkvvhfw30h63j7vq9dyhtc&rid=480w_s.jpg&ct=g"
                },
                "4k": {
                    "height": "2304",
                    "width": "2258",
                    "mp4_size": "3677192",
                    "mp4": "https://media2.giphy.com/media/1luY5uKUrILyQbwcKe/giphy-4k.mp4?cid=dc2d95a07pxei7gvj2qojhewywtkvvhfw30h63j7vq9dyhtc&rid=giphy-4k.mp4&ct=g"
                }
            },
            "user": {
                "avatar_url": "https://media1.giphy.com/avatars/chippythedog/wEeLMLZ5Cq9I.jpg",
                "banner_image": "https://media1.giphy.com/headers/chippythedog/ErEYf80CA5yq.jpg",
                "banner_url": "https://media1.giphy.com/headers/chippythedog/ErEYf80CA5yq.jpg",
                "profile_url": "https://giphy.com/chippythedog/",
                "username": "chippythedog",
                "display_name": "Chippy the Dog",
                "description": "Chippy is a little dog with a lot of love in his heart for you.\r\nYou can get Chippy's new book, If Chippy Was Your Dog, on Amazon and Etsy.",
                "instagram_url": "https://instagram.com/chippythedogbooks",
                "website_url": "https://etsy.me/2gAofU9",
                "is_verified": true
            },
            "analytics_response_payload": "e=Z2lmX2lkPTFsdVk1dUtVcklMeVFid2NLZSZldmVudF90eXBlPUdJRl9UUkVORElORyZjaWQ9ZGMyZDk1YTA3cHhlaTdndmoycW9qaGV3eXd0a3Z2aGZ3MzBoNjNqN3ZxOWR5aHRjJmN0PWc",
            "analytics": {
                "onload": {
                    "url": "https://giphy-analytics.giphy.com/v2/pingback_simple?analytics_response_payload=e%3DZ2lmX2lkPTFsdVk1dUtVcklMeVFid2NLZSZldmVudF90eXBlPUdJRl9UUkVORElORyZjaWQ9ZGMyZDk1YTA3cHhlaTdndmoycW9qaGV3eXd0a3Z2aGZ3MzBoNjNqN3ZxOWR5aHRjJmN0PWc&action_type=SEEN"
                },
                "onclick": {
                    "url": "https://giphy-analytics.giphy.com/v2/pingback_simple?analytics_response_payload=e%3DZ2lmX2lkPTFsdVk1dUtVcklMeVFid2NLZSZldmVudF90eXBlPUdJRl9UUkVORElORyZjaWQ9ZGMyZDk1YTA3cHhlaTdndmoycW9qaGV3eXd0a3Z2aGZ3MzBoNjNqN3ZxOWR5aHRjJmN0PWc&action_type=CLICK"
                },
                "onsent": {
                    "url": "https://giphy-analytics.giphy.com/v2/pingback_simple?analytics_response_payload=e%3DZ2lmX2lkPTFsdVk1dUtVcklMeVFid2NLZSZldmVudF90eXBlPUdJRl9UUkVORElORyZjaWQ9ZGMyZDk1YTA3cHhlaTdndmoycW9qaGV3eXd0a3Z2aGZ3MzBoNjNqN3ZxOWR5aHRjJmN0PWc&action_type=SENT"
                }
            }
        },
        {
            "type": "gif",
            "id": "7XfkZOCNuR1dcwaTjI",
            "url": "https://giphy.com/gifs/7XfkZOCNuR1dcwaTjI",
            "slug": "7XfkZOCNuR1dcwaTjI",
            "bitly_gif_url": "https://gph.is/g/ZnBNGyA",
            "bitly_url": "https://gph.is/g/ZnBNGyA",
            "embed_url": "https://giphy.com/embed/7XfkZOCNuR1dcwaTjI",
            "username": "robynmusto",
            "source": "",
            "title": "Happy Birthday GIF by Doxotto",
            "rating": "g",
            "content_url": "",
            "source_tld": "",
            "source_post_url": "",
            "is_sticker": 0,
            "import_datetime": "2021-08-23 00:18:34",
            "trending_datetime": "0000-00-00 00:00:00",
            "images": {
                "original": {
                    "height": "480",
                    "width": "480",
                    "size": "32701",
                    "url": "https://media4.giphy.com/media/7XfkZOCNuR1dcwaTjI/giphy.gif?cid=dc2d95a07pxei7gvj2qojhewywtkvvhfw30h63j7vq9dyhtc&rid=giphy.gif&ct=g",
                    "mp4_size": "31619",
                    "mp4": "https://media4.giphy.com/media/7XfkZOCNuR1dcwaTjI/giphy.mp4?cid=dc2d95a07pxei7gvj2qojhewywtkvvhfw30h63j7vq9dyhtc&rid=giphy.mp4&ct=g",
                    "webp_size": "21210",
                    "webp": "https://media4.giphy.com/media/7XfkZOCNuR1dcwaTjI/giphy.webp?cid=dc2d95a07pxei7gvj2qojhewywtkvvhfw30h63j7vq9dyhtc&rid=giphy.webp&ct=g",
                    "frames": "2",
                    "hash": "8a8626c9e3c4b7bf94e8fa6057ccc154"
                },
                "downsized": {
                    "height": "480",
                    "width": "480",
                    "size": "32701",
                    "url": "https://media4.giphy.com/media/7XfkZOCNuR1dcwaTjI/giphy.gif?cid=dc2d95a07pxei7gvj2qojhewywtkvvhfw30h63j7vq9dyhtc&rid=giphy.gif&ct=g"
                },
                "downsized_large": {
                    "height": "480",
                    "width": "480",
                    "size": "32701",
                    "url": "https://media4.giphy.com/media/7XfkZOCNuR1dcwaTjI/giphy.gif?cid=dc2d95a07pxei7gvj2qojhewywtkvvhfw30h63j7vq9dyhtc&rid=giphy.gif&ct=g"
                },
                "downsized_medium": {
                    "height": "480",
                    "width": "480",
                    "size": "32701",
                    "url": "https://media4.giphy.com/media/7XfkZOCNuR1dcwaTjI/giphy.gif?cid=dc2d95a07pxei7gvj2qojhewywtkvvhfw30h63j7vq9dyhtc&rid=giphy.gif&ct=g"
                },
                "downsized_small": {
                    "height": "480",
                    "width": "480",
                    "mp4_size": "28767",
                    "mp4": "https://media4.giphy.com/media/7XfkZOCNuR1dcwaTjI/giphy-downsized-small.mp4?cid=dc2d95a07pxei7gvj2qojhewywtkvvhfw30h63j7vq9dyhtc&rid=giphy-downsized-small.mp4&ct=g"
                },
                "downsized_still": {
                    "height": "480",
                    "width": "480",
                    "size": "32701",
                    "url": "https://media4.giphy.com/media/7XfkZOCNuR1dcwaTjI/giphy_s.gif?cid=dc2d95a07pxei7gvj2qojhewywtkvvhfw30h63j7vq9dyhtc&rid=giphy_s.gif&ct=g"
                },
                "fixed_height": {
                    "height": "200",
                    "width": "200",
                    "size": "9830",
                    "url": "https://media4.giphy.com/media/7XfkZOCNuR1dcwaTjI/200.gif?cid=dc2d95a07pxei7gvj2qojhewywtkvvhfw30h63j7vq9dyhtc&rid=200.gif&ct=g",
                    "mp4_size": "10560",
                    "mp4": "https://media4.giphy.com/media/7XfkZOCNuR1dcwaTjI/200.mp4?cid=dc2d95a07pxei7gvj2qojhewywtkvvhfw30h63j7vq9dyhtc&rid=200.mp4&ct=g",
                    "webp_size": "6996",
                    "webp": "https://media4.giphy.com/media/7XfkZOCNuR1dcwaTjI/200.webp?cid=dc2d95a07pxei7gvj2qojhewywtkvvhfw30h63j7vq9dyhtc&rid=200.webp&ct=g"
                },
                "fixed_height_downsampled": {
                    "height": "200",
                    "width": "200",
                    "size": "9830",
                    "url": "https://media4.giphy.com/media/7XfkZOCNuR1dcwaTjI/200_d.gif?cid=dc2d95a07pxei7gvj2qojhewywtkvvhfw30h63j7vq9dyhtc&rid=200_d.gif&ct=g",
                    "webp_size": "6896",
                    "webp": "https://media4.giphy.com/media/7XfkZOCNuR1dcwaTjI/200_d.webp?cid=dc2d95a07pxei7gvj2qojhewywtkvvhfw30h63j7vq9dyhtc&rid=200_d.webp&ct=g"
                },
                "fixed_height_small": {
                    "height": "100",
                    "width": "100",
                    "size": "4360",
                    "url": "https://media4.giphy.com/media/7XfkZOCNuR1dcwaTjI/100.gif?cid=dc2d95a07pxei7gvj2qojhewywtkvvhfw30h63j7vq9dyhtc&rid=100.gif&ct=g",
                    "mp4_size": "4712",
                    "mp4": "https://media4.giphy.com/media/7XfkZOCNuR1dcwaTjI/100.mp4?cid=dc2d95a07pxei7gvj2qojhewywtkvvhfw30h63j7vq9dyhtc&rid=100.mp4&ct=g",
                    "webp_size": "2674",
                    "webp": "https://media4.giphy.com/media/7XfkZOCNuR1dcwaTjI/100.webp?cid=dc2d95a07pxei7gvj2qojhewywtkvvhfw30h63j7vq9dyhtc&rid=100.webp&ct=g"
                },
                "fixed_height_small_still": {
                    "height": "100",
                    "width": "100",
                    "size": "2535",
                    "url": "https://media4.giphy.com/media/7XfkZOCNuR1dcwaTjI/100_s.gif?cid=dc2d95a07pxei7gvj2qojhewywtkvvhfw30h63j7vq9dyhtc&rid=100_s.gif&ct=g"
                },
                "fixed_height_still": {
                    "height": "200",
                    "width": "200",
                    "size": "5245",
                    "url": "https://media4.giphy.com/media/7XfkZOCNuR1dcwaTjI/200_s.gif?cid=dc2d95a07pxei7gvj2qojhewywtkvvhfw30h63j7vq9dyhtc&rid=200_s.gif&ct=g"
                },
                "fixed_width": {
                    "height": "200",
                    "width": "200",
                    "size": "9830",
                    "url": "https://media4.giphy.com/media/7XfkZOCNuR1dcwaTjI/200w.gif?cid=dc2d95a07pxei7gvj2qojhewywtkvvhfw30h63j7vq9dyhtc&rid=200w.gif&ct=g",
                    "mp4_size": "10560",
                    "mp4": "https://media4.giphy.com/media/7XfkZOCNuR1dcwaTjI/200w.mp4?cid=dc2d95a07pxei7gvj2qojhewywtkvvhfw30h63j7vq9dyhtc&rid=200w.mp4&ct=g",
                    "webp_size": "6996",
                    "webp": "https://media4.giphy.com/media/7XfkZOCNuR1dcwaTjI/200w.webp?cid=dc2d95a07pxei7gvj2qojhewywtkvvhfw30h63j7vq9dyhtc&rid=200w.webp&ct=g"
                },
                "fixed_width_downsampled": {
                    "height": "200",
                    "width": "200",
                    "size": "9830",
                    "url": "https://media4.giphy.com/media/7XfkZOCNuR1dcwaTjI/200w_d.gif?cid=dc2d95a07pxei7gvj2qojhewywtkvvhfw30h63j7vq9dyhtc&rid=200w_d.gif&ct=g",
                    "webp_size": "6896",
                    "webp": "https://media4.giphy.com/media/7XfkZOCNuR1dcwaTjI/200w_d.webp?cid=dc2d95a07pxei7gvj2qojhewywtkvvhfw30h63j7vq9dyhtc&rid=200w_d.webp&ct=g"
                },
                "fixed_width_small": {
                    "height": "100",
                    "width": "100",
                    "size": "4360",
                    "url": "https://media4.giphy.com/media/7XfkZOCNuR1dcwaTjI/100w.gif?cid=dc2d95a07pxei7gvj2qojhewywtkvvhfw30h63j7vq9dyhtc&rid=100w.gif&ct=g",
                    "mp4_size": "4712",
                    "mp4": "https://media4.giphy.com/media/7XfkZOCNuR1dcwaTjI/100w.mp4?cid=dc2d95a07pxei7gvj2qojhewywtkvvhfw30h63j7vq9dyhtc&rid=100w.mp4&ct=g",
                    "webp_size": "2674",
                    "webp": "https://media4.giphy.com/media/7XfkZOCNuR1dcwaTjI/100w.webp?cid=dc2d95a07pxei7gvj2qojhewywtkvvhfw30h63j7vq9dyhtc&rid=100w.webp&ct=g"
                },
                "fixed_width_small_still": {
                    "height": "100",
                    "width": "100",
                    "size": "2535",
                    "url": "https://media4.giphy.com/media/7XfkZOCNuR1dcwaTjI/100w_s.gif?cid=dc2d95a07pxei7gvj2qojhewywtkvvhfw30h63j7vq9dyhtc&rid=100w_s.gif&ct=g"
                },
                "fixed_width_still": {
                    "height": "200",
                    "width": "200",
                    "size": "5245",
                    "url": "https://media4.giphy.com/media/7XfkZOCNuR1dcwaTjI/200w_s.gif?cid=dc2d95a07pxei7gvj2qojhewywtkvvhfw30h63j7vq9dyhtc&rid=200w_s.gif&ct=g"
                },
                "looping": {
                    "mp4_size": "632660",
                    "mp4": "https://media4.giphy.com/media/7XfkZOCNuR1dcwaTjI/giphy-loop.mp4?cid=dc2d95a07pxei7gvj2qojhewywtkvvhfw30h63j7vq9dyhtc&rid=giphy-loop.mp4&ct=g"
                },
                "original_still": {
                    "height": "480",
                    "width": "480",
                    "size": "21977",
                    "url": "https://media4.giphy.com/media/7XfkZOCNuR1dcwaTjI/giphy_s.gif?cid=dc2d95a07pxei7gvj2qojhewywtkvvhfw30h63j7vq9dyhtc&rid=giphy_s.gif&ct=g"
                },
                "original_mp4": {
                    "height": "480",
                    "width": "480",
                    "mp4_size": "31619",
                    "mp4": "https://media4.giphy.com/media/7XfkZOCNuR1dcwaTjI/giphy.mp4?cid=dc2d95a07pxei7gvj2qojhewywtkvvhfw30h63j7vq9dyhtc&rid=giphy.mp4&ct=g"
                },
                "preview": {
                    "height": "480",
                    "width": "480",
                    "mp4_size": "28767",
                    "mp4": "https://media4.giphy.com/media/7XfkZOCNuR1dcwaTjI/giphy-preview.mp4?cid=dc2d95a07pxei7gvj2qojhewywtkvvhfw30h63j7vq9dyhtc&rid=giphy-preview.mp4&ct=g"
                },
                "preview_gif": {
                    "height": "480",
                    "width": "480",
                    "size": "46729",
                    "url": "https://media4.giphy.com/media/7XfkZOCNuR1dcwaTjI/giphy-preview.gif?cid=dc2d95a07pxei7gvj2qojhewywtkvvhfw30h63j7vq9dyhtc&rid=giphy-preview.gif&ct=g"
                },
                "preview_webp": {
                    "height": "480",
                    "width": "480",
                    "size": "21210",
                    "url": "https://media4.giphy.com/media/7XfkZOCNuR1dcwaTjI/giphy-preview.webp?cid=dc2d95a07pxei7gvj2qojhewywtkvvhfw30h63j7vq9dyhtc&rid=giphy-preview.webp&ct=g"
                },
                "hd": {
                    "height": "1920",
                    "width": "1920",
                    "mp4_size": "216969",
                    "mp4": "https://media4.giphy.com/media/7XfkZOCNuR1dcwaTjI/giphy-hd.mp4?cid=dc2d95a07pxei7gvj2qojhewywtkvvhfw30h63j7vq9dyhtc&rid=giphy-hd.mp4&ct=g"
                },
                "480w_still": {
                    "height": "480",
                    "width": "480",
                    "size": "32701",
                    "url": "https://media4.giphy.com/media/7XfkZOCNuR1dcwaTjI/480w_s.jpg?cid=dc2d95a07pxei7gvj2qojhewywtkvvhfw30h63j7vq9dyhtc&rid=480w_s.jpg&ct=g"
                },
                "4k": {
                    "height": "3840",
                    "width": "3840",
                    "mp4_size": "1496642",
                    "mp4": "https://media4.giphy.com/media/7XfkZOCNuR1dcwaTjI/giphy-4k.mp4?cid=dc2d95a07pxei7gvj2qojhewywtkvvhfw30h63j7vq9dyhtc&rid=giphy-4k.mp4&ct=g"
                }
            },
            "user": {
                "avatar_url": "https://media3.giphy.com/avatars/robynmusto/EBkQPO24OOR8.gif",
                "banner_image": "https://media3.giphy.com/headers/robynmusto/m7zsORSh77rS.gif",
                "banner_url": "https://media3.giphy.com/headers/robynmusto/m7zsORSh77rS.gif",
                "profile_url": "https://giphy.com/robynmusto/",
                "username": "robynmusto",
                "display_name": "Doxotto",
                "description": "",
                "instagram_url": "https://instagram.com/robynmusto",
                "website_url": "http://www.robynmusto.com/",
                "is_verified": true
            },
            "analytics_response_payload": "e=Z2lmX2lkPTdYZmtaT0NOdVIxZGN3YVRqSSZldmVudF90eXBlPUdJRl9UUkVORElORyZjaWQ9ZGMyZDk1YTA3cHhlaTdndmoycW9qaGV3eXd0a3Z2aGZ3MzBoNjNqN3ZxOWR5aHRjJmN0PWc",
            "analytics": {
                "onload": {
                    "url": "https://giphy-analytics.giphy.com/v2/pingback_simple?analytics_response_payload=e%3DZ2lmX2lkPTdYZmtaT0NOdVIxZGN3YVRqSSZldmVudF90eXBlPUdJRl9UUkVORElORyZjaWQ9ZGMyZDk1YTA3cHhlaTdndmoycW9qaGV3eXd0a3Z2aGZ3MzBoNjNqN3ZxOWR5aHRjJmN0PWc&action_type=SEEN"
                },
                "onclick": {
                    "url": "https://giphy-analytics.giphy.com/v2/pingback_simple?analytics_response_payload=e%3DZ2lmX2lkPTdYZmtaT0NOdVIxZGN3YVRqSSZldmVudF90eXBlPUdJRl9UUkVORElORyZjaWQ9ZGMyZDk1YTA3cHhlaTdndmoycW9qaGV3eXd0a3Z2aGZ3MzBoNjNqN3ZxOWR5aHRjJmN0PWc&action_type=CLICK"
                },
                "onsent": {
                    "url": "https://giphy-analytics.giphy.com/v2/pingback_simple?analytics_response_payload=e%3DZ2lmX2lkPTdYZmtaT0NOdVIxZGN3YVRqSSZldmVudF90eXBlPUdJRl9UUkVORElORyZjaWQ9ZGMyZDk1YTA3cHhlaTdndmoycW9qaGV3eXd0a3Z2aGZ3MzBoNjNqN3ZxOWR5aHRjJmN0PWc&action_type=SENT"
                }
            }
        }
    ],
    "pagination": {
        "total_count": 3874,
        "count": 5,
        "offset": 0
    },
    "meta": {
        "status": 200,
        "msg": "OK",
        "response_id": "7pxei7gvj2qojhewywtkvvhfw30h63j7vq9dyhtc"
    }
}
